autofeats/__init__.py
autofeats/features/group_by.py
autofeats/features/window.py
autofeats/make_features.py
autofeats/types.py
autofeats-0.1.2.dist-info/WHEEL
autofeats-0.1.2.dist-info/METADATA
autofeats-0.1.2.dist-info/RECORD
