Metadata-Version: 2.1
Name: autofeats
Version: 0.1.2
Summary: 
Home-page: https://github.com/felipesassi/autofeats
Author: Felipe Sassi
Author-email: felipesassi@outlook.com
Requires-Python: >=3.8,<4.0
Classifier: Programming Language :: Python :: 3
Classifier: Programming Language :: Python :: 3.10
Classifier: Programming Language :: Python :: 3.8
Classifier: Programming Language :: Python :: 3.9
Requires-Dist: pandas (>=1.5.3,<2.0.0)
Requires-Dist: pyspark (>=3.3.1,<4.0.0)
Project-URL: Repository, https://github.com/felipesassi/autofeats
